slapi/__init__.py
slapi-0.0.6.dist-info/LICENSE
slapi-0.0.6.dist-info/METADATA
slapi-0.0.6.dist-info/WHEEL
slapi-0.0.6.dist-info/entry_points.txt
slapi-0.0.6.dist-info/top_level.txt
slapi-0.0.6.dist-info/RECORD
